forte/__init__.py
forte/pipeline.py
forte/pipeline_component.py
forte/process_job.py
forte/process_manager.py
forte/train_pipeline.py
forte/train_preprocessor.py
forte/version.py
forte/command_line/__init__.py
forte/command_line/generate_ontology/__init__.py
forte/command_line/generate_ontology/__main__.py
forte/common/__init__.py
forte/common/configurable.py
forte/common/configuration.py
forte/common/constants.py
forte/common/exception.py
forte/common/resources.py
forte/data/__init__.py
forte/data/base_extractor.py
forte/data/base_pack.py
forte/data/base_reader.py
forte/data/base_store.py
forte/data/batchers.py
forte/data/caster.py
forte/data/common_entry_utils.py
forte/data/container.py
forte/data/data_pack.py
forte/data/data_pack_dataset.py
forte/data/data_store.py
forte/data/data_utils.py
forte/data/data_utils_io.py
forte/data/index.py
forte/data/multi_pack.py
forte/data/selector.py
forte/data/span.py
forte/data/types.py
forte/data/vocabulary.py
forte/data/converter/__init__.py
forte/data/converter/converter.py
forte/data/converter/feature.py
forte/data/extractors/__init__.py
forte/data/extractors/attribute_extractor.py
forte/data/extractors/char_extractor.py
forte/data/extractors/relation_extractor.py
forte/data/extractors/seqtagging_extractor.py
forte/data/extractors/subword_extractor.py
forte/data/ontology/__init__.py
forte/data/ontology/code_generation_exceptions.py
forte/data/ontology/code_generation_objects.py
forte/data/ontology/core.py
forte/data/ontology/ontology_code_const.py
forte/data/ontology/ontology_code_generator.py
forte/data/ontology/top.py
forte/data/ontology/utils.py
forte/data/ontology/validation_schema.json
forte/data/readers/__init__.py
forte/data/readers/ag_news_reader.py
forte/data/readers/audio_reader.py
forte/data/readers/classification_reader.py
forte/data/readers/conll03_reader.py
forte/data/readers/conllu_ud_reader.py
forte/data/readers/deserialize_reader.py
forte/data/readers/html_reader.py
forte/data/readers/largemovie_reader.py
forte-0.2.0.dist-info/LICENSE
forte-0.2.0.dist-info/METADATA
forte-0.2.0.dist-info/WHEEL
forte-0.2.0.dist-info/entry_points.txt
forte-0.2.0.dist-info/top_level.txt
forte-0.2.0.dist-info/RECORD
