Metadata-Version: 2.1
Name: forte
Version: 0.2.0
Summary: Forte is extensible framework for building composable and modularized NLP workflows.
Home-page: https://github.com/asyml/forte
License: Apache License Version 2.0
Platform: any
Classifier: Intended Audience :: Developers
Classifier: Intended Audience :: Education
Classifier: Intended Audience :: Science/Research
Classifier: Operating System :: OS Independent
Classifier: Programming Language :: Python
Classifier: Programming Language :: Python :: 3.6
Classifier: Programming Language :: Python :: 3.7
License-File: LICENSE
Requires-Dist: sortedcontainers (>=2.1.0)
Requires-Dist: numpy (>=1.16.6)
Requires-Dist: jsonpickle (>=1.4)
Requires-Dist: pyyaml (>=5.4)
Requires-Dist: smart-open (>=1.8.4)
Requires-Dist: typed-astunparse (>=2.1.4)
Requires-Dist: funcsigs (>=1.0.2)
Requires-Dist: typed-ast (>=1.5.0)
Requires-Dist: jsonschema (>=3.0.2)
Requires-Dist: typing-inspect (>=0.6.0)
Requires-Dist: asyml-utilities
Requires-Dist: typing (>=3.7.4) ; python_version < "3.5"
Requires-Dist: dataclasses (~=0.7) ; python_version < "3.7"
Requires-Dist: importlib-resources (>=5.1.4) ; python_version < "3.7"
Provides-Extra: audio_ext
Requires-Dist: soundfile (>=0.10.3) ; extra == 'audio_ext'
Provides-Extra: data_aug
Requires-Dist: transformers (>=4.15.0) ; extra == 'data_aug'
Requires-Dist: nltk ; extra == 'data_aug'
Requires-Dist: texar-pytorch (>=0.1.4) ; extra == 'data_aug'
Requires-Dist: requests ; extra == 'data_aug'
Provides-Extra: extractor
Requires-Dist: texar-pytorch (>=0.1.4) ; extra == 'extractor'
Provides-Extra: ir
Requires-Dist: texar-pytorch (>=0.1.4) ; extra == 'ir'
Requires-Dist: tensorflow (>=1.15.0) ; extra == 'ir'
Provides-Extra: models
Requires-Dist: torch (>=1.1.0) ; extra == 'models'
Requires-Dist: torchtext (==0.4.0) ; extra == 'models'
Requires-Dist: tqdm (>=4.36.1) ; extra == 'models'
Requires-Dist: texar-pytorch (>=0.1.4) ; extra == 'models'
Requires-Dist: tensorflow (>=1.15.0) ; extra == 'models'
Provides-Extra: nlp
Requires-Dist: texar-pytorch (>=0.1.4) ; extra == 'nlp'
Provides-Extra: remote
Requires-Dist: fastapi (>=0.65.2) ; extra == 'remote'
Requires-Dist: uvicorn (>=0.14.0) ; extra == 'remote'
Requires-Dist: requests ; extra == 'remote'
Provides-Extra: stave
Requires-Dist: stave (>=0.0.1.dev12) ; extra == 'stave'
Provides-Extra: test
Requires-Dist: ddt ; extra == 'test'
Requires-Dist: testfixtures ; extra == 'test'
Requires-Dist: testbook ; extra == 'test'
Requires-Dist: termcolor ; extra == 'test'
Requires-Dist: transformers (>=4.15.0) ; extra == 'test'
Requires-Dist: nltk ; extra == 'test'
Provides-Extra: wikipedia
Requires-Dist: rdflib (==4.2.2) ; extra == 'wikipedia'
